CLGame/__init__.py
CLGame/engine.py
CLGame-1.0.1.dist-info/LICENSE
CLGame-1.0.1.dist-info/METADATA
CLGame-1.0.1.dist-info/WHEEL
CLGame-1.0.1.dist-info/top_level.txt
CLGame-1.0.1.dist-info/RECORD
