Metadata-Version: 2.1
Name: CLGame
Version: 1.0.1
Summary: Module that helps to create games in terminal
Home-page: https://github.com/K0RSY/CLGame
Author: Korsy
Author-email: pgeorg@gmail.com
Project-URL: Wiki, https://github.com/K0RSY/CLGame/wiki
Keywords: game engine cli tui terminal console
Classifier: Programming Language :: Python :: 3.11
Classifier: License :: OSI Approved :: GNU General Public License v3 or later (GPLv3+)
Classifier: Operating System :: OS Independent
Requires-Python: >=3.10
License-File: LICENSE
Requires-Dist: playsound>=1.3.0
Requires-Dist: pynput>=1.7.7
